test_management_sync/__init__.py
test_management_sync/manager.py
test_management_sync/model.py
test_management_sync/service.py
test_management_sync/util.py
test_management_sync/zephyr/__init__.py
test_management_sync/zephyr/actions/__init__.py
test_management_sync/zephyr/actions/attachments.py
test_management_sync/zephyr/actions/planning.py
test_management_sync/zephyr/actions/preferences.py
test_management_sync/zephyr/actions/requirement.py
test_management_sync/zephyr/actions/requirement_tree.py
test_management_sync/zephyr/actions/search.py
test_management_sync/zephyr/actions/testcase.py
test_management_sync/zephyr/actions/testcase_tree.py
test_management_sync/zephyr/actions/user.py
test_management_sync/zephyr/model/__init__.py
test_management_sync/zephyr/model/attachments.py
test_management_sync/zephyr/model/field_util.py
test_management_sync/zephyr/model/planning.py
test_management_sync/zephyr/model/preferences.py
test_management_sync/zephyr/model/requirements.py
test_management_sync/zephyr/model/search.py
test_management_sync/zephyr/model/testcases.py
test_management_sync/zephyr/model/user.py
test_management_sync/zephyr/service.py
test_management_sync/zephyr/session.py
test_management_sync-0.0.2rc12910606653.dist-info/LICENSE.txt
test_management_sync-0.0.2rc12910606653.dist-info/METADATA
test_management_sync-0.0.2rc12910606653.dist-info/WHEEL
test_management_sync-0.0.2rc12910606653.dist-info/RECORD
