Metadata-Version: 2.1
Name: test-management-sync
Version: 0.0.2rc12910606653
Summary: API to syncronize test result with test-management tool
License: Apache-2.0
Author: developer
Author-email: developer@exactpro.com
Requires-Python: >=3.9
Classifier: License :: OSI Approved :: Apache Software License
Classifier: Programming Language :: Python :: 3
Classifier: Programming Language :: Python :: 3.9
Classifier: Programming Language :: Python :: 3.10
Classifier: Programming Language :: Python :: 3.11
Requires-Dist: dataclasses-json
Requires-Dist: requests
